imaginaition/__init__.py
imaginaition/__main__.py
imaginaition/cut.py
imaginaition/help.py
imaginaition/imaginaition_logging.py
imaginaition/imagine.py
imaginaition-0.1.3.dist-info/LICENSE.md
imaginaition-0.1.3.dist-info/METADATA
imaginaition-0.1.3.dist-info/WHEEL
imaginaition-0.1.3.dist-info/entry_points.txt
imaginaition-0.1.3.dist-info/top_level.txt
imaginaition-0.1.3.dist-info/RECORD
