Metadata-Version: 2.1
Name: imaginaition
Version: 0.1.3
Author: jtpotato
License: GNU GENERAL PUBLIC LICENSE
Project-URL: homepage, https://github.com/jtpotato/imaginaition
Requires-Python: >=3.9
License-File: LICENSE.md
Requires-Dist: auto-editor
Requires-Dist: rgbprint
